MANIFEST.in
install.txt
readme.txt
setup.cfg
setup.py
webskine/__init__.py
webskine/template.py
webskine/wsgiapp.py
webskine.egg-info/PKG-INFO
webskine.egg-info/SOURCES.txt
webskine.egg-info/dependency_links.txt
webskine.egg-info/entry_points.txt
webskine.egg-info/not-zip-safe
webskine.egg-info/paster_plugins.txt
webskine.egg-info/requires.txt
webskine.egg-info/top_level.txt
webskine/paster_templates/server.ini_tmpl
webskine/paster_templates/htdocs/css/style.css
webskine/paster_templates/htdocs/images/add.png
webskine/paster_templates/htdocs/images/delete.png
webskine/paster_templates/htdocs/images/edit.png
webskine/paster_templates/htdocs/js/cookies.js
webskine/paster_templates/htdocs/js/jquery.js
webskine/paster_templates/htdocs/js/json.js
webskine/paster_templates/htdocs/js/webskine.js
webskine/paster_templates/htdocs/js/tinymce/jscripts/tiny_mce/.tiny_mce.js.swp
webskine/paster_templates/htdocs/js/tinymce/jscripts/tiny_mce/blank.htm
webskine/paster_templates/htdocs/js/tinymce/jscripts/tiny_mce/license.txt
webskine/paster_templates/htdocs/js/tinymce/jscripts/tiny_mce/tiny_mce.js
webskine/paster_templates/htdocs/js/tinymce/jscripts/tiny_mce/tiny_mce_popup.js
webskine/paster_templates/htdocs/js/tinymce/jscripts/tiny_mce/tiny_mce_src.js
webskine/paster_templates/htdocs/js/tinymce/jscripts/tiny_mce/langs/en.js
webskine/paster_templates/htdocs/js/tinymce/jscripts/tiny_mce/langs/readme.txt
webskine/paster_templates/htdocs/js/tinymce/jscripts/tiny_mce/plugins/readme.txt
webskine/paster_templates/htdocs/js/tinymce/jscripts/tiny_mce/plugins/_template/editor_plugin.js
webskine/paster_templates/htdocs/js/tinymce/jscripts/tiny_mce/plugins/_template/editor_plugin_src.js
webskine/paster_templates/htdocs/js/tinymce/jscripts/tiny_mce/plugins/_template/popup.htm
webskine/paster_templates/htdocs/js/tinymce/jscripts/tiny_mce/plugins/_template/readme.txt
webskine/paster_templates/htdocs/js/tinymce/jscripts/tiny_mce/plugins/_template/images/template.gif
webskine/paster_templates/htdocs/js/tinymce/jscripts/tiny_mce/plugins/_template/langs/en.js
webskine/paster_templates/htdocs/js/tinymce/jscripts/tiny_mce/plugins/advhr/editor_plugin.js
webskine/paster_templates/htdocs/js/tinymce/jscripts/tiny_mce/plugins/advhr/editor_plugin_src.js
