Metadata-Version: 1.0
Name: webskine
Version: 0.2
Summary: A simple WSGI blog.
Home-page: http://dealmeida.net/projects/webskine
Author: Roberto De Almeida
Author-email: roberto@dealmeida.net
License: MIT
Keywords: wsgi blog
Platform: UNKNOWN
